cdk_stepfunctions_redshift/__init__.py
cdk_stepfunctions_redshift/py.typed
cdk_stepfunctions_redshift/_jsii/__init__.py
cdk_stepfunctions_redshift/_jsii/cdk-stepfunctions-redshift@1.123.0.jsii.tgz
cdk_stepfunctions_redshift-1.123.0.dist-info/LICENSE
cdk_stepfunctions_redshift-1.123.0.dist-info/METADATA
cdk_stepfunctions_redshift-1.123.0.dist-info/WHEEL
cdk_stepfunctions_redshift-1.123.0.dist-info/top_level.txt
cdk_stepfunctions_redshift-1.123.0.dist-info/RECORD
