Metadata-Version: 2.1
Name: cdk-stepfunctions-redshift
Version: 1.123.0
Summary: A JSII construct lib to build AWS Serverless infrastructure to orchestrate Redshift using AWS stepfunctions.
Home-page: https://github.com/aws-samples/cdk-stepfunctions-redshift.git
Author: Peter Van Bouwel<pbbouwel@amazon.com>
License: MIT-0
Project-URL: Source, https://github.com/aws-samples/cdk-stepfunctions-redshift.git
Platform: UNKNOWN
Classifier: Intended Audience :: Developers
Classifier: Operating System :: OS Independent
Classifier: Programming Language :: JavaScript
Classifier: Programming Language :: Python :: 3 :: Only
Classifier: Programming Language :: Python :: 3.6
Classifier: Programming Language :: Python :: 3.7
Classifier: Programming Language :: Python :: 3.8
Classifier: Programming Language :: Python :: 3.9
Classifier: Typing :: Typed
Classifier: Development Status :: 5 - Production/Stable
Classifier: License :: OSI Approved
Requires-Python: >=3.6
License-File: LICENSE
Requires-Dist: aws-cdk.aws-dynamodb (==1.123.0)
Requires-Dist: aws-cdk.aws-ec2 (==1.123.0)
Requires-Dist: aws-cdk.aws-events-targets (==1.123.0)
Requires-Dist: aws-cdk.aws-events (==1.123.0)
Requires-Dist: aws-cdk.aws-iam (==1.123.0)
Requires-Dist: aws-cdk.aws-kms (==1.123.0)
Requires-Dist: aws-cdk.aws-lambda-event-sources (==1.123.0)
Requires-Dist: aws-cdk.aws-lambda-python (==1.123.0)
Requires-Dist: aws-cdk.aws-lambda (==1.123.0)
Requires-Dist: aws-cdk.aws-logs (==1.123.0)
Requires-Dist: aws-cdk.aws-redshift (==1.123.0)
Requires-Dist: aws-cdk.aws-sam (==1.123.0)
Requires-Dist: aws-cdk.aws-sqs (==1.123.0)
Requires-Dist: aws-cdk.aws-stepfunctions-tasks (==1.123.0)
Requires-Dist: aws-cdk.aws-stepfunctions (==1.123.0)
Requires-Dist: aws-cdk.core (==1.123.0)
Requires-Dist: aws-solutions-constructs.aws-eventbridge-sqs (==1.123.0)
Requires-Dist: aws-solutions-constructs.aws-lambda-dynamodb (==1.123.0)
Requires-Dist: aws-solutions-constructs.aws-sqs-lambda (==1.123.0)
Requires-Dist: constructs (<4.0.0,>=3.2.27)
Requires-Dist: jsii (<2.0.0,>=1.35.0)
Requires-Dist: publication (>=0.0.3)
